tests/__init__.py
tests/yet/__init__.py
tests/yet/test_config.py
yet/__init__.py
yet/main.py
yet/config/__init__.py
yet/config/config.py
yet/config/videoscache.py
yet/config/yet.conf
yet/ui/__init__.py
yet/ui/infobar.py
yet/ui/infowidget.py
yet/ui/rect.py
yet/ui/scrollablewidget.py
yet/ui/subswidget.py
yet/ui/videoswidget.py
yet/ui/widget.py
yet/ui/window.py
yet/yt/__init__.py
yet/yt/channel.py
yet/yt/ytdlwrapper.py
ye_tui-0.1.6.dist-info/LICENSE
ye_tui-0.1.6.dist-info/METADATA
ye_tui-0.1.6.dist-info/WHEEL
ye_tui-0.1.6.dist-info/entry_points.txt
ye_tui-0.1.6.dist-info/top_level.txt
ye_tui-0.1.6.dist-info/RECORD
