Metadata-Version: 2.1
Name: ye-tui
Version: 0.1.6
Summary: yet is a console (kind of rss) application to download youtube videos.
Home-page: https://github.com/nevarman/yet
Author: mushroomrisotto
Author-email: pypi.gib@aleeas.com
License: GPL3
Platform: UNKNOWN
Classifier: Environment :: Console
Classifier: Environment :: Console :: Curses
Classifier: Intended Audience :: Developers
Classifier: Intended Audience :: End Users/Desktop
Classifier: Intended Audience :: System Administrators
Classifier: License :: OSI Approved :: GNU General Public License v3 (GPLv3)
Classifier: Operating System :: MacOS
Classifier: Operating System :: POSIX
Classifier: Operating System :: Unix
Classifier: Programming Language :: Python :: 3.6
Classifier: Topic :: Desktop Environment
Classifier: Topic :: Utilities
Requires-Python: >=3.6
Requires-Dist: xmltodict
Requires-Dist: youtube-dl
